tobe/__init__.py
tobe/tobe.py
tobe/version.py
tobe-0.4.2.dist-info/LICENSE.txt
tobe-0.4.2.dist-info/METADATA
tobe-0.4.2.dist-info/WHEEL
tobe-0.4.2.dist-info/entry_points.txt
tobe-0.4.2.dist-info/top_level.txt
tobe-0.4.2.dist-info/RECORD
